pg2avro/__init__.py
pg2avro/pg2avro.py
pg2avro-0.2.5.dist-info/LICENSE
pg2avro-0.2.5.dist-info/METADATA
pg2avro-0.2.5.dist-info/WHEEL
pg2avro-0.2.5.dist-info/top_level.txt
pg2avro-0.2.5.dist-info/RECORD
