Metadata-Version: 2.1
Name: pg2avro
Version: 0.2.5
Summary: Utility generating avro files from postgres.
Home-page: https://github.com/kiwicom/pg2avro
Author: Milan Lukac
Author-email: milan.lukac@kiwi.com
License: MIT
Platform: UNKNOWN
Classifier: Development Status :: 3 - Alpha
Classifier: Intended Audience :: Developers
Classifier: Environment :: Plugins
Classifier: Operating System :: OS Independent
Classifier: Programming Language :: Python
Classifier: Programming Language :: Python :: 3
Classifier: Programming Language :: Python :: 3.6
Classifier: Programming Language :: Python :: 3.7
Classifier: License :: OSI Approved :: MIT License
Requires-Python: >=3.6
License-File: LICENSE
Requires-Dist: sqlalchemy (>=1.2)
Requires-Dist: psycopg2 (>=2.7)
